CHANGES.txt
CONTRIBUTORS.txt
README.txt
bootstrap.py
buildout.cfg
setup.py
collective/__init__.py
collective.recipe.mockedeggs.egg-info/PKG-INFO
collective.recipe.mockedeggs.egg-info/SOURCES.txt
collective.recipe.mockedeggs.egg-info/dependency_links.txt
collective.recipe.mockedeggs.egg-info/entry_points.txt
collective.recipe.mockedeggs.egg-info/namespace_packages.txt
collective.recipe.mockedeggs.egg-info/not-zip-safe
collective.recipe.mockedeggs.egg-info/requires.txt
collective.recipe.mockedeggs.egg-info/top_level.txt
collective/recipe/__init__.py
collective/recipe/mockedeggs/README.txt
collective/recipe/mockedeggs/__init__.py
collective/recipe/mockedeggs/tests/__init__.py
collective/recipe/mockedeggs/tests/test_docs.py