Metadata-Version: 1.0
Name: collective.recipe.mockedeggs
Version: 1.0rc1
Summary: A recipe to simulate eggs for non eggs modules installed at python level
Home-page: http://svn.plone.org/svn/collective/collective.recipe.mockedeggs
Author: Thomas Desvenain
Author-email: thomas.desvenain@ingeniweb.com
License: ZPL
Platform: UNKNOWN
Classifier: Framework :: Buildout
Classifier: Intended Audience :: Developers
Classifier: Topic :: Software Development :: Build Tools
Classifier: License :: OSI Approved :: Zope Public License
